topicmodels/__init__.py
topicmodels/corpus.py
topicmodels/eval_measure.py
topicmodels/ldann.py
topicmodels/stt_lemmas.json
topicmodels/stt_lemmas_lstm.json
topicmodels/topic_modelling_lstm.py
topicmodels/topic_modelling_nn.py
topicmodels/topic_modelling_trans.py
topicmodels/utility_module.py
topicmodels-0.0.20.dist-info/LICENSE
topicmodels-0.0.20.dist-info/METADATA
topicmodels-0.0.20.dist-info/WHEEL
topicmodels-0.0.20.dist-info/top_level.txt
topicmodels-0.0.20.dist-info/RECORD
